marimo_functions/__init__.py
marimo_functions/function.py
marimo_functions/pick_function.py
marimo_functions/helpers/__init__.py
marimo_functions/helpers/settings.py
marimo_functions/sklearn/__init__.py
marimo_functions/sklearn/manifold/__init__.py
marimo_functions/sklearn/manifold/isomap.py
marimo_functions/sklearn/manifold/locally_linear_embedding.py
marimo_functions/sklearn/manifold/mds.py
marimo_functions/sklearn/manifold/spectral_embedding.py
marimo_functions/sklearn/manifold/tsne.py
marimo_functions-0.2.0.dist-info/licenses/LICENSE
marimo_functions-0.2.0.dist-info/METADATA
marimo_functions-0.2.0.dist-info/WHEEL
marimo_functions-0.2.0.dist-info/top_level.txt
marimo_functions-0.2.0.dist-info/RECORD
