Metadata-Version: 2.4
Name: marimo-functions
Version: 0.2.0
Summary: Flexible interface for defining functions with marimo UI inputs 
Author-email: Sam Minot <sminot@fredhutch.org>
License-Expression: MIT
Project-URL: Homepage, https://github.com/fredhutch/marimo-functions
Project-URL: Issues, https://github.com/fredhutch/marimo-functions/issues
Requires-Python: >=3.11
License-File: LICENSE
Requires-Dist: marimo>=0.15.1
Requires-Dist: numpy>=2.3.2
Requires-Dist: pandas>=2.3.2
Requires-Dist: plotly>=6.3.0
Requires-Dist: scikit-learn>=1.7.1
Requires-Dist: scipy>=1.16.1
Dynamic: license-file
